fr24_client/__init__.py
fr24_client/api/__init__.py
fr24_client/api/airlines_light_api.py
fr24_client/api/airports_full_api.py
fr24_client/api/airports_light_api.py
fr24_client/api/flight_tracks_api.py
fr24_client/api/historic_flight_positions_full_api.py
fr24_client/api/historic_flight_positions_light_api.py
fr24_client/api/live_flight_positions_full_api.py
fr24_client/api/live_flight_positions_light_api.py
fr24_client/api/usage_api.py
fr24_client/api_client.py
fr24_client/api_response.py
fr24_client/configuration.py
fr24_client/exceptions.py
fr24_client/models/__init__.py
fr24_client/models/airline.py
fr24_client/models/airport.py
fr24_client/models/airport_detailed.py
fr24_client/models/country.py
fr24_client/models/flight.py
fr24_client/models/flight_positions.py
fr24_client/models/flight_tracks.py
fr24_client/models/flight_tracks_tracks_inner.py
fr24_client/models/get_airlines_light400_response.py
fr24_client/models/get_airlines_light404_response.py
fr24_client/models/get_airports_full400_response.py
fr24_client/models/get_airports_full404_response.py
fr24_client/models/get_api_usage200_response.py
fr24_client/models/get_flights_tracks400_response.py
fr24_client/models/get_flights_tracks404_response.py
fr24_client/models/get_live_flight_positions_full200_response.py
fr24_client/models/get_live_flight_positions_full400_response.py
fr24_client/models/get_live_flight_positions_light200_response.py
fr24_client/models/timezone.py
fr24_client/models/usage_log_summary.py
fr24_client/py.typed
fr24_client/rest.py
fr24_client-1.0.0.dist-info/METADATA
fr24_client-1.0.0.dist-info/WHEEL
fr24_client-1.0.0.dist-info/RECORD
